textodon/__init__.py
textodon/cli.py
textodon/textodon.py
textodon/welcome.py
textodon-0.1.0.dist-info/LICENSE
textodon-0.1.0.dist-info/METADATA
textodon-0.1.0.dist-info/WHEEL
textodon-0.1.0.dist-info/entry_points.txt
textodon-0.1.0.dist-info/top_level.txt
textodon-0.1.0.dist-info/RECORD
