Metadata-Version: 2.1
Name: textodon
Version: 0.1.0
Summary: A TUI mastodon client & CLI
Home-page: https://github.com/RatulMaharaj/textodon
Author: Ratul Maharaj
Author-email: ratulmaharaj@looped.co.za
License: MIT license
Keywords: textodon
Classifier: Development Status :: 2 - Pre-Alpha
Classifier: Intended Audience :: Developers
Classifier: License :: OSI Approved :: MIT License
Classifier: Natural Language :: English
Classifier: Programming Language :: Python :: 3
Classifier: Programming Language :: Python :: 3.6
Classifier: Programming Language :: Python :: 3.7
Classifier: Programming Language :: Python :: 3.8
Requires-Python: >=3.6
License-File: LICENSE
Requires-Dist: Click (>=7.0)
